medevalkit/__init__.py
medevalkit/bootstrap.py
medevalkit/calibration.py
medevalkit/compare.py
medevalkit/evaluate.py
medevalkit/fairness.py
medevalkit/metrics.py
medevalkit/plots.py
medevalkit/simulation.py
medevalkit/survival.py
medevalkit/threshold.py
medevalkit/tradeoff.py
medevalkit-0.1.3.2.dist-info/licenses/LICENSE
medevalkit-0.1.3.2.dist-info/METADATA
medevalkit-0.1.3.2.dist-info/WHEEL
medevalkit-0.1.3.2.dist-info/top_level.txt
medevalkit-0.1.3.2.dist-info/RECORD
